token_quotes/__init__.py
token_quotes/api_clients.py
token_quotes/cli.py
token_quotes/utils.py
token_quotes/wallet_manager_latest.py
token_quotes-0.4.0.dist-info/LICENSE.txt
token_quotes-0.4.0.dist-info/METADATA
token_quotes-0.4.0.dist-info/WHEEL
token_quotes-0.4.0.dist-info/entry_points.txt
token_quotes-0.4.0.dist-info/RECORD
