Metadata-Version: 2.1
Name: token-quotes
Version: 0.4.0
Summary: Calls Covalent API to get token quotes for a list of crypto wallet addresses
Author: Xavier Armitage
Author-email: xtarmitage@gmail.com
Requires-Python: >=3.11,<4.0
Classifier: Programming Language :: Python :: 3
Classifier: Programming Language :: Python :: 3.11
Classifier: Programming Language :: Python :: 3.12
Requires-Dist: aiohttp (>=3.10.5,<4.0.0)
Requires-Dist: cachetools (>=5.5.0,<6.0.0)
Requires-Dist: pandas (>=2.2.2,<3.0.0)
Requires-Dist: python-dotenv (>=1.0.1,<2.0.0)
Requires-Dist: pyyaml (>=6.0.1,<7.0.0)
Requires-Dist: types-cachetools (>=5.5.0.20240820,<6.0.0.0)
